{
    "comments":
        {
            "data":
                [
                    
                    {
                        "can_remove":"1",
                        "created_time":"2011-09-01T01:24:06+0000",
                        "from":
                            {
                                "id":"578684050",
                                "name":"Nicole Hamlett"
                            },
                        "id":"728337349_10150304830577350_18430050",
                        "message":"Please be safe Shannon. Don't get hit by any busses (hug)"
                    },
                    
                    {
                        "can_remove":"1",
                        "created_time":"2011-09-01T01:30:44+0000",
                        "from":
                            {
                                "id":"653106427",
                                "name":"Sarah Burns Feyl"
                            },
                        "id":"728337349_10150304830577350_18430151",
                        "message":"Safe and enjoyable travels to you all!"
                    },
                    
                    {
                        "can_remove":"1",
                        "created_time":"2011-09-01T01:35:16+0000",
                        "from":
                            {
                                "id":"1400595350",
                                "name":"Peter Oehler"
                            },
                        "id":"728337349_10150304830577350_18430230",
                        "message":"Have a memorable time and keep us informed as you can. Safe travels."
                    },
                    
                    {
                        "can_remove":"1",
                        "created_time":"2011-09-01T01:46:59+0000",
                        "from":
                            {
                                "id":"1504001963",
                                "name":"Dan Prendergast"
                            },
                        "id":"728337349_10150304830577350_18430443",
                        "message":"Safe travels, don't forget to post pics from the top of Kilimanjaro!  :-)"
                    },
                    
                    {
                        "can_remove":"1",
                        "created_time":"2011-09-01T01:48:10+0000",
                        "from":
                            {
                                "id":"1431258542",
                                "name":"Ginny Norris-Napier"
                            },
                        "id":"728337349_10150304830577350_18430463",
                        "likes":1,
                        "message":"Slow slow slow and tons of water you'll be great!  Say hello to her from me   It changed my life!",
                        "user_likes":"1"
                    },
                    
                    {
                        "can_remove":"1",
                        "created_time":"2011-09-01T01:48:30+0000",
                        "from":
                            {
                                "id":"1431258542",
                                "name":"Ginny Norris-Napier"
                            },
                        "id":"728337349_10150304830577350_18430465",
                        "message":"The safari rocks too!"
                    },
                    
                    {
                        "can_remove":"1",
                        "created_time":"2011-09-01T01:51:59+0000",
                        "from":
                            {
                                "id":"100000144862020",
                                "name":"Cathleen Farrell"
                            },
                        "id":"728337349_10150304830577350_18430524",
                        "message":"Stay safe and have an amazing time!!"
                    },
                    
                    {
                        "can_remove":"1",
                        "created_time":"2011-09-01T02:11:31+0000",
                        "from":
                            {
                                "id":"770382751",
                                "name":"Jennifer Jumper"
                            },
                        "id":"728337349_10150304830577350_18430830",
                        "message":"Same here.  Let's just get there already!"
                    },
                    
                    {
                        "can_remove":"1",
                        "created_time":"2011-09-01T02:13:01+0000",
                        "from":
                            {
                                "id":"776976832",
                                "name":"Rob Nardone"
                            },
                        "id":"728337349_10150304830577350_18430865",
                        "message":"Have a great trip."
                    },
                    
                    {
                        "can_remove":"1",
                        "created_time":"2011-09-01T02:26:43+0000",
                        "from":
                            {
                                "id":"749199277",
                                "name":"Jeremy Collins"
                            },
                        "id":"728337349_10150304830577350_18431071",
                        "message":"So stoked for you guys! Hope every moment is amazing! Be safe, and I can't wait to see the photos!"
                    },
                    
                    {
                        "can_remove":"1",
                        "created_time":"2011-09-01T02:27:40+0000",
                        "from":
                            {
                                "id":"659131965",
                                "name":"Ray Yu"
                            },
                        "id":"728337349_10150304830577350_18431087",
                        "message":"Be safe and have lots of fun!!!"
                    },
                    
                    {
                        "can_remove":"1",
                        "created_time":"2011-09-01T02:46:45+0000",
                        "from":
                            {
                                "id":"1358432029",
                                "name":"Robin Amison Reinhart"
                            },
                        "id":"728337349_10150304830577350_18431412",
                        "message":"Oh wow!  Have an amazing trip and be safe!!!"
                    },
                    
                    {
                        "can_remove":"1",
                        "created_time":"2011-09-01T03:46:30+0000",
                        "from":
                            {
                                "id":"1554010659",
                                "name":"Donna Peronace"
                            },
                        "id":"728337349_10150304830577350_18432273",
                        "message":"Safe travels.  I'm sure it will be an amazing experience!"
                    },
                    
                    {
                        "can_remove":"1",
                        "created_time":"2011-09-02T23:46:44+0000",
                        "from":
                            {
                                "id":"1175507065",
                                "name":"Debra Klopfenstein"
                            },
                        "id":"728337349_10150304830577350_18467503",
                        "message":"Have a great time!"
                    }
                ]
        },
    "id":"20110901_2_012135",
    "link":"http:\/\/www.facebook.com\/728337349\/posts\/10150304830577350",
    "message":"Thnaks for all the well-wishes on the Kilimanjaro trip! I'm going with seven other people on the hike (my Dad, college-era friends, and post-college friends). Afterwards, we're getting a couple more people joining us and doing a safari. We leave Friday... it's very exciting and nerve-wracking at this point. I just want to be going now!",
    "publishedDate":"2011-09-01T01:21:35+00:00",
    "source":"facebook",
    "title":null,
    "type":"status",
    "via":"Facebook",
    "~orig":
        {
            "actions":
                [
                    
                    {
                        "link":"http:\/\/www.facebook.com\/728337349\/posts\/10150304830577350",
                        "name":"Comment"
                    },
                    
                    {
                        "link":"http:\/\/www.facebook.com\/728337349\/posts\/10150304830577350",
                        "name":"Like"
                    }
                ],
            "comments":
                {
                    "data":
                        [
                            
                            {
                                "can_remove":"1",
                                "created_time":"2011-09-01T01:24:06+0000",
                                "from":
                                    {
                                        "id":"578684050",
                                        "name":"Nicole Hamlett"
                                    },
                                "id":"728337349_10150304830577350_18430050",
                                "message":"Please be safe Shannon. Don't get hit by any busses (hug)"
                            },
                            
                            {
                                "can_remove":"1",
                                "created_time":"2011-09-01T01:30:44+0000",
                                "from":
                                    {
                                        "id":"653106427",
                                        "name":"Sarah Burns Feyl"
                                    },
                                "id":"728337349_10150304830577350_18430151",
                                "message":"Safe and enjoyable travels to you all!"
                            },
                            
                            {
                                "can_remove":"1",
                                "created_time":"2011-09-01T01:35:16+0000",
                                "from":
                                    {
                                        "id":"1400595350",
                                        "name":"Peter Oehler"
                                    },
                                "id":"728337349_10150304830577350_18430230",
                                "message":"Have a memorable time and keep us informed as you can. Safe travels."
                            },
                            
                            {
                                "can_remove":"1",
                                "created_time":"2011-09-01T01:46:59+0000",
                                "from":
                                    {
                                        "id":"1504001963",
                                        "name":"Dan Prendergast"
                                    },
                                "id":"728337349_10150304830577350_18430443",
                                "message":"Safe travels, don't forget to post pics from the top of Kilimanjaro!  :-)"
                            },
                            
                            {
                                "can_remove":"1",
                                "created_time":"2011-09-01T01:48:10+0000",
                                "from":
                                    {
                                        "id":"1431258542",
                                        "name":"Ginny Norris-Napier"
                                    },
                                "id":"728337349_10150304830577350_18430463",
                                "likes":1,
                                "message":"Slow slow slow and tons of water you'll be great!  Say hello to her from me   It changed my life!",
                                "user_likes":"1"
                            },
                            
                            {
                                "can_remove":"1",
                                "created_time":"2011-09-01T01:48:30+0000",
                                "from":
                                    {
                                        "id":"1431258542",
                                        "name":"Ginny Norris-Napier"
                                    },
                                "id":"728337349_10150304830577350_18430465",
                                "message":"The safari rocks too!"
                            },
                            
                            {
                                "can_remove":"1",
                                "created_time":"2011-09-01T01:51:59+0000",
                                "from":
                                    {
                                        "id":"100000144862020",
                                        "name":"Cathleen Farrell"
                                    },
                                "id":"728337349_10150304830577350_18430524",
                                "message":"Stay safe and have an amazing time!!"
                            },
                            
                            {
                                "can_remove":"1",
                                "created_time":"2011-09-01T02:11:31+0000",
                                "from":
                                    {
                                        "id":"770382751",
                                        "name":"Jennifer Jumper"
                                    },
                                "id":"728337349_10150304830577350_18430830",
                                "message":"Same here.  Let's just get there already!"
                            },
                            
                            {
                                "can_remove":"1",
                                "created_time":"2011-09-01T02:13:01+0000",
                                "from":
                                    {
                                        "id":"776976832",
                                        "name":"Rob Nardone"
                                    },
                                "id":"728337349_10150304830577350_18430865",
                                "message":"Have a great trip."
                            },
                            
                            {
                                "can_remove":"1",
                                "created_time":"2011-09-01T02:26:43+0000",
                                "from":
                                    {
                                        "id":"749199277",
                                        "name":"Jeremy Collins"
                                    },
                                "id":"728337349_10150304830577350_18431071",
                                "message":"So stoked for you guys! Hope every moment is amazing! Be safe, and I can't wait to see the photos!"
                            },
                            
                            {
                                "can_remove":"1",
                                "created_time":"2011-09-01T02:27:40+0000",
                                "from":
                                    {
                                        "id":"659131965",
                                        "name":"Ray Yu"
                                    },
                                "id":"728337349_10150304830577350_18431087",
                                "message":"Be safe and have lots of fun!!!"
                            },
                            
                            {
                                "can_remove":"1",
                                "created_time":"2011-09-01T02:46:45+0000",
                                "from":
                                    {
                                        "id":"1358432029",
                                        "name":"Robin Amison Reinhart"
                                    },
                                "id":"728337349_10150304830577350_18431412",
                                "message":"Oh wow!  Have an amazing trip and be safe!!!"
                            },
                            
                            {
                                "can_remove":"1",
                                "created_time":"2011-09-01T03:46:30+0000",
                                "from":
                                    {
                                        "id":"1554010659",
                                        "name":"Donna Peronace"
                                    },
                                "id":"728337349_10150304830577350_18432273",
                                "message":"Safe travels.  I'm sure it will be an amazing experience!"
                            },
                            
                            {
                                "can_remove":"1",
                                "created_time":"2011-09-02T23:46:44+0000",
                                "from":
                                    {
                                        "id":"1175507065",
                                        "name":"Debra Klopfenstein"
                                    },
                                "id":"728337349_10150304830577350_18467503",
                                "message":"Have a great time!"
                            }
                        ]
                },
            "created_time":"2011-09-01T01:21:35+0000",
            "from":
                {
                    "id":"728337349",
                    "name":"Shannon Posniewski"
                },
            "id":"728337349_10150304830577350",
            "likes":
                {
                    "count":25,
                    "data":
                        [
                            
                            {
                                "id":"100000764207008",
                                "name":"Beth Homicz"
                            },
                            
                            {
                                "id":"100001886337239",
                                "name":"Ernie Collins"
                            },
                            
                            {
                                "id":"906725466",
                                "name":"Rick Dakan"
                            },
                            
                            {
                                "id":"100000533714233",
                                "name":"Kate Bankson"
                            }
                        ]
                },
            "message":"Thnaks for all the well-wishes on the Kilimanjaro trip! I'm going with seven other people on the hike (my Dad, college-era friends, and post-college friends). Afterwards, we're getting a couple more people joining us and doing a safari. We leave Friday... it's very exciting and nerve-wracking at this point. I just want to be going now!",
            "privacy":
                {
                    "allow":"0",
                    "deny":"0",
                    "description":"Friends of Friends",
                    "value":"FRIENDS_OF_FRIENDS"
                },
            "type":"status",
            "updated_time":"2011-09-02T23:46:44+0000"
        }
}