{
    "comments":
        {
            "data":
                [
                    
                    {
                        "can_remove":"1",
                        "created_time":"2011-11-13T02:16:25+0000",
                        "from":
                            {
                                "id":"1358432029",
                                "name":"Robin Amison Reinhart"
                            },
                        "id":"728337349_10150399974482350_19681171",
                        "message":"blah"
                    },
                    
                    {
                        "can_remove":"1",
                        "created_time":"2011-11-13T03:02:14+0000",
                        "from":
                            {
                                "id":"1532923484",
                                "name":"Mary Zinkievich"
                            },
                        "id":"728337349_10150399974482350_19681665",
                        "likes":1,
                        "message":"Damn that's bad! You should've come to hometown buffet and had a shitty dinner with us! "
                    },
                    
                    {
                        "can_remove":"1",
                        "created_time":"2011-11-13T05:08:51+0000",
                        "from":
                            {
                                "id":"1361476318",
                                "name":"Michele Liguori"
                            },
                        "id":"728337349_10150399974482350_19682698",
                        "message":"I had doughnuts for lunch. "
                    }
                ]
        },
    "id":"20111113_2_013055",
    "link":"http:\/\/www.facebook.com\/728337349\/posts\/10150399974482350",
    "message":"To be added to the list of Life's Regrets: Having pretzels and onion dip for dinner.",
    "publishedDate":"2011-11-13T01:30:55+00:00",
    "source":"facebook",
    "title":null,
    "type":"status",
    "via":"Twitter",
    "~orig":
        {
            "actions":
                [
                    
                    {
                        "link":"http:\/\/www.facebook.com\/728337349\/posts\/10150399974482350",
                        "name":"Comment"
                    },
                    
                    {
                        "link":"http:\/\/www.facebook.com\/728337349\/posts\/10150399974482350",
                        "name":"Like"
                    },
                    
                    {
                        "link":"http:\/\/twitter.com\/posniewski?utm_source=fb&utm_medium=fb&utm_campaign=posniewski&utm_content=135530044813619200",
                        "name":"@posniewski on Twitter"
                    }
                ],
            "application":
                {
                    "canvas_name":"twitter",
                    "id":"2231777543",
                    "name":"Twitter",
                    "namespace":"twitter"
                },
            "comments":
                {
                    "data":
                        [
                            
                            {
                                "can_remove":"1",
                                "created_time":"2011-11-13T02:16:25+0000",
                                "from":
                                    {
                                        "id":"1358432029",
                                        "name":"Robin Amison Reinhart"
                                    },
                                "id":"728337349_10150399974482350_19681171",
                                "message":"blah"
                            },
                            
                            {
                                "can_remove":"1",
                                "created_time":"2011-11-13T03:02:14+0000",
                                "from":
                                    {
                                        "id":"1532923484",
                                        "name":"Mary Zinkievich"
                                    },
                                "id":"728337349_10150399974482350_19681665",
                                "likes":1,
                                "message":"Damn that's bad! You should've come to hometown buffet and had a shitty dinner with us! "
                            },
                            
                            {
                                "can_remove":"1",
                                "created_time":"2011-11-13T05:08:51+0000",
                                "from":
                                    {
                                        "id":"1361476318",
                                        "name":"Michele Liguori"
                                    },
                                "id":"728337349_10150399974482350_19682698",
                                "message":"I had doughnuts for lunch. "
                            }
                        ],
                    "paging":
                        {
                            "next":"https:\/\/graph.facebook.com\/728337349_10150399974482350\/comments?access_token=202981499713630|f0e29551db76a6dbed4c8d5e.1-728337349|1C7yRomzW6wd2-7ogKO4lZLcdEI&limit=25&offset=25&__after_id=728337349_10150399974482350_19682698"
                        }
                },
            "created_time":"2011-11-13T01:30:55+0000",
            "from":
                {
                    "id":"728337349",
                    "name":"Shannon Posniewski"
                },
            "icon":"https:\/\/fbcdn-photos-a.akamaihd.net\/photos-ak-snc1\/v27562\/23\/2231777543\/app_2_2231777543_9553.gif",
            "id":"728337349_10150399974482350",
            "likes":
                {
                    "count":4,
                    "data":
                        [
                            
                            {
                                "id":"1134692210",
                                "name":"Shelley Day Posniewski"
                            },
                            
                            {
                                "id":"778159473",
                                "name":"Iwan Axt"
                            },
                            
                            {
                                "id":"559128594",
                                "name":"Matt Healey"
                            },
                            
                            {
                                "id":"634898579",
                                "name":"Kat O'Leary"
                            }
                        ]
                },
            "message":"To be added to the list of Life's Regrets: Having pretzels and onion dip for dinner.",
            "privacy":
                {
                    "allow":"0",
                    "deny":"0",
                    "description":"Friends of Friends",
                    "value":"FRIENDS_OF_FRIENDS"
                },
            "type":"status",
            "updated_time":"2011-11-13T05:08:51+0000"
        }
}