{
    "comments":
        {
            "data":
                [
                    
                    {
                        "can_remove":"1",
                        "created_time":"2013-12-08T19:49:55+0000",
                        "from":
                            {
                                "id":"728337349",
                                "name":"Shannon Posniewski"
                            },
                        "id":"10152058779522350_247534596",
                        "like_count":1,
                        "message":"So far, this app is winning because it makes a good image on mobile. Three or four more to try...",
                        "user_likes":"0"
                    },
                    
                    {
                        "can_remove":"1",
                        "created_time":"2013-12-08T21:37:08+0000",
                        "from":
                            {
                                "id":"728337349",
                                "name":"Shannon Posniewski"
                            },
                        "id":"10152058779522350_247536108",
                        "like_count":0,
                        "message":"That said, I can't export my route with timing information, which I like to have. I can do that with RunKeeper.",
                        "user_likes":"0"
                    }
                ]
        },
    "id":"20131208_2_182617",
    "link":"http:\/\/www.mapmyrun.com\/workout\/443588003",
    "mapurl":"http:\/\/share.abvio.com\/\/\/\/\/Runmeter-.kml",
    "mapurl_cached":"http:\/\/foamtotem.org\/daily\/runs\/20131208_2_182617.jpg",
    "message":"Good run today. (Trying a few tracking apps. Why does this one not auto-capitalize?) #runhappy",
    "publishedDate":"2013-12-08T18:26:17+00:00",
    "source":"facebook",
    "type":"run",
    "via":"MapMyRun",
    "~orig":
        {
            "application":
                {
                    "id":"43211574282",
                    "name":"MapMyRun",
                    "namespace":"mapmyrunapp"
                },
            "comments":
                {
                    "data":
                        [
                            
                            {
                                "can_remove":"1",
                                "created_time":"2013-12-08T19:49:55+0000",
                                "from":
                                    {
                                        "id":"728337349",
                                        "name":"Shannon Posniewski"
                                    },
                                "id":"10152058779522350_247534596",
                                "like_count":1,
                                "message":"So far, this app is winning because it makes a good image on mobile. Three or four more to try...",
                                "user_likes":"0"
                            },
                            
                            {
                                "can_remove":"1",
                                "created_time":"2013-12-08T21:37:08+0000",
                                "from":
                                    {
                                        "id":"728337349",
                                        "name":"Shannon Posniewski"
                                    },
                                "id":"10152058779522350_247536108",
                                "like_count":0,
                                "message":"That said, I can't export my route with timing information, which I like to have. I can do that with RunKeeper.",
                                "user_likes":"0"
                            }
                        ],
                    "paging":
                        {
                            "cursors":
                                {
                                    "after":"Mg==",
                                    "before":"MQ=="
                                }
                        }
                },
            "data":
                {
                    "course":
                        {
                            "id":"570609159693964",
                            "title":"Ran 3.65 mi on 12\/8\/2013",
                            "type":"fitness.course",
                            "url":"http:\/\/www.mapmyrun.com\/workout\/443588003"
                        }
                },
            "end_time":"2013-12-08T17:47:07+0000",
            "from":
                {
                    "id":"728337349",
                    "name":"Shannon Posniewski"
                },
            "id":"10152058779522350",
            "likes":
                {
                    "can_like":"1",
                    "count":1,
                    "data":
                        [
                            
                            {
                                "id":"1361476318",
                                "name":"Michele Liguori"
                            }
                        ],
                    "paging":
                        {
                            "cursors":
                                {
                                    "after":"MTM2MTQ3NjMxOA==",
                                    "before":"MTM2MTQ3NjMxOA=="
                                }
                        },
                    "user_likes":"0"
                },
            "message":"Good run today. (Trying a few tracking apps. Why does this one not auto-capitalize?) #runhappy",
            "no_feed_story":"0",
            "publish_time":"2013-12-08T18:26:17+0000",
            "start_time":"2013-12-08T17:47:07+0000",
            "type":"fitness.runs"
        }
}