{
    "comments":
        {
            "data":
                [
                    
                    {
                        "can_remove":"1",
                        "created_time":"2014-07-14T23:05:16+0000",
                        "from":
                            {
                                "id":"1361476318",
                                "name":"Michele Liguori"
                            },
                        "id":"10152554248217350_10152554256247350",
                        "like_count":0,
                        "message":"I approve. :)",
                        "user_likes":"0"
                    },
                    
                    {
                        "can_remove":"1",
                        "created_time":"2014-07-14T23:19:22+0000",
                        "from":
                            {
                                "id":"1134692210",
                                "name":"Shelley Day Posniewski"
                            },
                        "id":"10152554248217350_10152554276882350",
                        "like_count":0,
                        "message":"Apologies to Maureen Sherman.We got to the bottom of Oil Mill Hill and the car hung a left. :)",
                        "message_tags":
                            [
                                
                                {
                                    "id":"1551470973",
                                    "length":15,
                                    "name":"Maureen Sherman",
                                    "offset":13,
                                    "type":"user"
                                }
                            ],
                        "user_likes":"0"
                    },
                    
                    {
                        "can_remove":"1",
                        "created_time":"2014-07-15T01:52:34+0000",
                        "from":
                            {
                                "id":"1400595350",
                                "name":"Peter Oehler"
                            },
                        "id":"10152554248217350_10152554509362350",
                        "like_count":1,
                        "message":"Do you want to (eat) a snowman?",
                        "user_likes":"0"
                    },
                    
                    {
                        "can_remove":"1",
                        "created_time":"2014-07-15T02:58:39+0000",
                        "from":
                            {
                                "id":"100000449847369",
                                "name":"Carol Kuhn"
                            },
                        "id":"10152554248217350_10152554619397350",
                        "like_count":0,
                        "message":"medium twist con please. FedEx to Kansas?",
                        "user_likes":"0"
                    },
                    
                    {
                        "can_remove":"1",
                        "created_time":"2014-07-16T19:39:39+0000",
                        "from":
                            {
                                "id":"1533771332",
                                "name":"Kathy Hartley"
                            },
                        "id":"10152554248217350_10152558258147350",
                        "like_count":0,
                        "message":"Carol, if you get east before the place closes, I'll treat!",
                        "user_likes":"0"
                    }
                ]
        },
    "id":"20140714_2_230052",
    "image":"https:\/\/scontent-b.xx.fbcdn.net\/hphotos-xpa1\/v\/t1.0-9\/10537419_10152554248217350_6783362097841619087_n.jpg?oh=0162ec24e3b712f00f29969e65082adb&oe=543F048A",
    "image_height":"666",
    "image_width":"500",
    "link":"https:\/\/www.facebook.com\/photo.php?fbid=10152554248217350&set=a.449479422349.249021.728337349&type=1",
    "message":"A hot day in Lansingburgh can mean only one thing...",
    "picture_cached":"http:\/\/foamtotem.org\/daily\/cache\/20140714_2_230052.jpg",
    "publishedDate":"2014-07-14T23:00:52+00:00",
    "source":"facebook",
    "type":"photo",
    "via":"Facebook",
    "~orig":
        {
            "actions":
                [
                    
                    {
                        "link":"https:\/\/www.facebook.com\/728337349\/posts\/10152554248287350",
                        "name":"Comment"
                    },
                    
                    {
                        "link":"https:\/\/www.facebook.com\/728337349\/posts\/10152554248287350",
                        "name":"Like"
                    }
                ],
            "application":
                {
                    "id":"350685531728",
                    "name":"Facebook for Android",
                    "namespace":"fbandroid"
                },
            "comments":
                {
                    "data":
                        [
                            
                            {
                                "can_remove":"1",
                                "created_time":"2014-07-14T23:05:16+0000",
                                "from":
                                    {
                                        "id":"1361476318",
                                        "name":"Michele Liguori"
                                    },
                                "id":"10152554248217350_10152554256247350",
                                "like_count":0,
                                "message":"I approve. :)",
                                "user_likes":"0"
                            },
                            
                            {
                                "can_remove":"1",
                                "created_time":"2014-07-14T23:19:22+0000",
                                "from":
                                    {
                                        "id":"1134692210",
                                        "name":"Shelley Day Posniewski"
                                    },
                                "id":"10152554248217350_10152554276882350",
                                "like_count":0,
                                "message":"Apologies to Maureen Sherman.We got to the bottom of Oil Mill Hill and the car hung a left. :)",
                                "message_tags":
                                    [
                                        
                                        {
                                            "id":"1551470973",
                                            "length":15,
                                            "name":"Maureen Sherman",
                                            "offset":13,
                                            "type":"user"
                                        }
                                    ],
                                "user_likes":"0"
                            },
                            
                            {
                                "can_remove":"1",
                                "created_time":"2014-07-15T01:52:34+0000",
                                "from":
                                    {
                                        "id":"1400595350",
                                        "name":"Peter Oehler"
                                    },
                                "id":"10152554248217350_10152554509362350",
                                "like_count":1,
                                "message":"Do you want to (eat) a snowman?",
                                "user_likes":"0"
                            },
                            
                            {
                                "can_remove":"1",
                                "created_time":"2014-07-15T02:58:39+0000",
                                "from":
                                    {
                                        "id":"100000449847369",
                                        "name":"Carol Kuhn"
                                    },
                                "id":"10152554248217350_10152554619397350",
                                "like_count":0,
                                "message":"medium twist con please. FedEx to Kansas?",
                                "user_likes":"0"
                            },
                            
                            {
                                "can_remove":"1",
                                "created_time":"2014-07-16T19:39:39+0000",
                                "from":
                                    {
                                        "id":"1533771332",
                                        "name":"Kathy Hartley"
                                    },
                                "id":"10152554248217350_10152558258147350",
                                "like_count":0,
                                "message":"Carol, if you get east before the place closes, I'll treat!",
                                "user_likes":"0"
                            }
                        ],
                    "paging":
                        {
                            "cursors":
                                {
                                    "after":"NQ==",
                                    "before":"MQ=="
                                }
                        }
                },
            "created_time":"2014-07-14T23:00:52+0000",
            "from":
                {
                    "id":"728337349",
                    "name":"Shannon Posniewski"
                },
            "icon":"https:\/\/fbstatic-a.akamaihd.net\/rsrc.php\/v2\/yx\/r\/og8V99JVf8G.gif",
            "id":"728337349_10152554248287350",
            "likes":
                {
                    "data":
                        [
                            
                            {
                                "id":"100007015535170",
                                "name":"Eduardo Lucero"
                            },
                            
                            {
                                "id":"1384816520",
                                "name":"Dawn Yates Gerlica"
                            },
                            
                            {
                                "id":"100000266633627",
                                "name":"Barbara Vorce"
                            },
                            
                            {
                                "id":"100000449847369",
                                "name":"Carol Kuhn"
                            },
                            
                            {
                                "id":"1175507065",
                                "name":"Debra Klopfenstein"
                            },
                            
                            {
                                "id":"1554010659",
                                "name":"Donna Peronace"
                            },
                            
                            {
                                "id":"100000962093789",
                                "name":"Marilyn Harris Collins"
                            },
                            
                            {
                                "id":"1805796131",
                                "name":"Katherine Murray"
                            },
                            
                            {
                                "id":"763724037",
                                "name":"Caleb Sorensen"
                            },
                            
                            {
                                "id":"100000296483750",
                                "name":"Cheryl Elkins"
                            },
                            
                            {
                                "id":"764999708",
                                "name":"Isaiah Sorensen"
                            },
                            
                            {
                                "id":"1564660698",
                                "name":"Bob Gilmore"
                            },
                            
                            {
                                "id":"1522387343",
                                "name":"Craig Zinkievich"
                            },
                            
                            {
                                "id":"653106427",
                                "name":"Sarah Burns Feyl"
                            },
                            
                            {
                                "id":"770382751",
                                "name":"Jenn Jumper"
                            },
                            
                            {
                                "id":"1151461337",
                                "name":"Michael Curley"
                            },
                            
                            {
                                "id":"578684050",
                                "name":"Nicole Hamlett"
                            },
                            
                            {
                                "id":"1504001963",
                                "name":"Dan Prendergast"
                            },
                            
                            {
                                "id":"668734147",
                                "name":"Lisa Ann Strand"
                            },
                            
                            {
                                "id":"1394434850",
                                "name":"Andrew Gosden"
                            },
                            
                            {
                                "id":"704886534",
                                "name":"Christa Burns"
                            },
                            
                            {
                                "id":"100002818047778",
                                "name":"Elke Blaetz"
                            },
                            
                            {
                                "id":"765009060",
                                "name":"Brianna Sorensen Fezza"
                            },
                            
                            {
                                "id":"1361476318",
                                "name":"Michele Liguori"
                            },
                            
                            {
                                "id":"1245484058",
                                "name":"Sarah Rain"
                            }
                        ],
                    "paging":
                        {
                            "cursors":
                                {
                                    "after":"MTI0NTQ4NDA1OA==",
                                    "before":"MTAwMDA3MDE1NTM1MTcw"
                                }
                        }
                },
            "link":"https:\/\/www.facebook.com\/photo.php?fbid=10152554248217350&set=a.449479422349.249021.728337349&type=1&relevant_count=1",
            "message":"A hot day in Lansingburgh can mean only one thing...",
            "object_id":"10152554248217350",
            "picture":"https:\/\/fbcdn-sphotos-d-a.akamaihd.net\/hphotos-ak-xpa1\/v\/t1.0-9\/s130x130\/10537419_10152554248217350_6783362097841619087_n.jpg?oh=93a45e0aa35a99b74e6560635eccf025&oe=543D6093&__gda__=1414079084_a8d1dc39da9d1c03ba3f9e29151f2e31",
            "privacy":
                {
                    "allow":"",
                    "deny":"",
                    "description":"Public",
                    "friends":"",
                    "networks":"",
                    "value":"EVERYONE"
                },
            "status_type":"added_photos",
            "to":
                {
                    "data":
                        [
                            
                            {
                                "id":"1134692210",
                                "name":"Shelley Day Posniewski"
                            }
                        ]
                },
            "type":"photo",
            "updated_time":"2014-07-16T19:39:39+0000",
            "with_tags":
                {
                    "data":
                        [
                            
                            {
                                "id":"1134692210",
                                "name":"Shelley Day Posniewski"
                            }
                        ]
                }
        }
}