{
    "caption":"kottke.org",
    "comments":
        {
            "data":
                [
                    
                    {
                        "can_remove":"1",
                        "created_time":"2014-07-26T23:11:19+0000",
                        "from":
                            {
                                "id":"1522387343",
                                "name":"Craig Zinkievich"
                            },
                        "id":"10152579436372350_10152580814397350",
                        "like_count":0,
                        "message":"I need a t-shirt!!",
                        "user_likes":"0"
                    }
                ]
        },
    "description":"Magisterial. (via @moleitau)",
    "id":"20140726_2_121312",
    "link":"http:\/\/kottke.org\/14\/07\/werner-the-herzog",
    "message":"Epic.",
    "name":"Werner the Herzog",
    "picture":"https:\/\/fbexternal-a.akamaihd.net\/safe_image.php?d=AQD7xl0c_87QTDxj&w=154&h=154&url=http%3A%2F%2Fkottke.org%2Fimages%2Fside%2Fenginehosting.gif",
    "picture_cached":"http:\/\/foamtotem.org\/daily\/cache\/20140726_2_121312.gif",
    "publishedDate":"2014-07-26T12:13:12+00:00",
    "source":"facebook",
    "type":"link",
    "via":"Facebook for Android",
    "~orig":
        {
            "actions":
                [
                    
                    {
                        "link":"https:\/\/www.facebook.com\/728337349\/posts\/10152579436372350",
                        "name":"Comment"
                    },
                    
                    {
                        "link":"https:\/\/www.facebook.com\/728337349\/posts\/10152579436372350",
                        "name":"Like"
                    }
                ],
            "application":
                {
                    "id":"350685531728",
                    "name":"Facebook for Android",
                    "namespace":"fbandroid"
                },
            "caption":"kottke.org",
            "comments":
                {
                    "data":
                        [
                            
                            {
                                "can_remove":"1",
                                "created_time":"2014-07-26T23:11:19+0000",
                                "from":
                                    {
                                        "id":"1522387343",
                                        "name":"Craig Zinkievich"
                                    },
                                "id":"10152579436372350_10152580814397350",
                                "like_count":0,
                                "message":"I need a t-shirt!!",
                                "user_likes":"0"
                            }
                        ],
                    "paging":
                        {
                            "cursors":
                                {
                                    "after":"MQ==",
                                    "before":"MQ=="
                                }
                        }
                },
            "created_time":"2014-07-26T12:13:12+0000",
            "description":"Magisterial. (via @moleitau)",
            "from":
                {
                    "id":"728337349",
                    "name":"Shannon Posniewski"
                },
            "icon":"https:\/\/fbstatic-a.akamaihd.net\/rsrc.php\/v2\/yD\/r\/aS8ecmYRys0.gif",
            "id":"728337349_10152579436372350",
            "likes":
                {
                    "data":
                        [
                            
                            {
                                "id":"1074936085",
                                "name":"Denis Korkh"
                            },
                            
                            {
                                "id":"770382751",
                                "name":"Jenn Jumper"
                            }
                        ],
                    "paging":
                        {
                            "cursors":
                                {
                                    "after":"NzcwMzgyNzUx",
                                    "before":"MTA3NDkzNjA4NQ=="
                                }
                        }
                },
            "link":"http:\/\/kottke.org\/14\/07\/werner-the-herzog",
            "message":"Epic.",
            "name":"Werner the Herzog",
            "picture":"https:\/\/fbexternal-a.akamaihd.net\/safe_image.php?d=AQD7xl0c_87QTDxj&w=154&h=154&url=http%3A%2F%2Fkottke.org%2Fimages%2Fside%2Fenginehosting.gif",
            "privacy":
                {
                    "allow":"",
                    "deny":"",
                    "description":"Public",
                    "friends":"",
                    "networks":"",
                    "value":"EVERYONE"
                },
            "status_type":"shared_story",
            "type":"link",
            "updated_time":"2014-07-26T23:11:19+0000"
        }
}