{
    "comments":
        {
            "data":
                [
                    
                    {
                        "can_remove":"1",
                        "created_time":"2015-07-27T01:17:09+0000",
                        "from":
                            {
                                "id":"10203509649367805",
                                "name":"Curt Krone"
                            },
                        "id":"10153493373097350_10153493373407350",
                        "like_count":1,
                        "message":"wow",
                        "user_likes":"1"
                    },
                    
                    {
                        "can_remove":"1",
                        "created_time":"2015-07-27T01:17:22+0000",
                        "from":
                            {
                                "id":"10203509649367805",
                                "name":"Curt Krone"
                            },
                        "id":"10153493373097350_10153493374222350",
                        "like_count":1,
                        "message":"have all the originals upstairs",
                        "user_likes":"1"
                    },
                    
                    {
                        "can_remove":"1",
                        "created_time":"2015-07-27T01:19:37+0000",
                        "from":
                            {
                                "id":"728337349",
                                "name":"Shannon Posniewski"
                            },
                        "id":"10153493373097350_10153493386227350",
                        "like_count":1,
                        "message":"I think the originals are easier to read! I had relied on the kindness of others for my Doom Patrol reading back in the day and figured that it was about time I paid the creators.",
                        "user_likes":"0"
                    },
                    
                    {
                        "can_remove":"1",
                        "created_time":"2015-07-27T01:25:55+0000",
                        "from":
                            {
                                "id":"10203509649367805",
                                "name":"Curt Krone"
                            },
                        "id":"10153493373097350_10153493406137350",
                        "like_count":0,
                        "message":"yeah, those huge bound volumes are pretty ungainly",
                        "user_likes":"0"
                    },
                    
                    {
                        "can_remove":"1",
                        "created_time":"2015-07-27T02:26:28+0000",
                        "from":
                            {
                                "id":"10203444793744799",
                                "name":"Michele Liguori"
                            },
                        "id":"10153493373097350_10153493487672350",
                        "like_count":1,
                        "message":"Time to sift through the long boxes...",
                        "user_likes":"0"
                    }
                ]
        },
    "id":"20150727_2_011650",
    "image":"https:\/\/scontent.xx.fbcdn.net\/hphotos-xfp1\/v\/t1.0-9\/11796460_10153493373097350_4574787842559235164_n.jpg?oh=b31bc0c3fc10f95badc1c0fb5086dc1a&oe=564E4753",
    "image_height":"375",
    "image_width":"500",
    "link":"https:\/\/www.facebook.com\/photo.php?fbid=10153493373097350&set=a.449479422349.249021.728337349&type=1",
    "message":"Just finished reading the 1000+ page Doom Patrol Omnibus (the Grant Morrison run) and boy are my arms tired!",
    "picture_cached":"http:\/\/foamtotem.org\/daily\/cache\/20150727_2_011650.jpg",
    "publishedDate":"2015-07-27T01:16:50+00:00",
    "source":"facebook",
    "type":"photo",
    "via":"Facebook",
    "~orig":
        {
            "actions":
                [
                    
                    {
                        "link":"https:\/\/www.facebook.com\/728337349\/posts\/10153493373097350",
                        "name":"Comment"
                    },
                    
                    {
                        "link":"https:\/\/www.facebook.com\/728337349\/posts\/10153493373097350",
                        "name":"Like"
                    }
                ],
            "comments":
                {
                    "data":
                        [
                            
                            {
                                "can_remove":"1",
                                "created_time":"2015-07-27T01:17:09+0000",
                                "from":
                                    {
                                        "id":"10203509649367805",
                                        "name":"Curt Krone"
                                    },
                                "id":"10153493373097350_10153493373407350",
                                "like_count":1,
                                "message":"wow",
                                "user_likes":"1"
                            },
                            
                            {
                                "can_remove":"1",
                                "created_time":"2015-07-27T01:17:22+0000",
                                "from":
                                    {
                                        "id":"10203509649367805",
                                        "name":"Curt Krone"
                                    },
                                "id":"10153493373097350_10153493374222350",
                                "like_count":1,
                                "message":"have all the originals upstairs",
                                "user_likes":"1"
                            },
                            
                            {
                                "can_remove":"1",
                                "created_time":"2015-07-27T01:19:37+0000",
                                "from":
                                    {
                                        "id":"728337349",
                                        "name":"Shannon Posniewski"
                                    },
                                "id":"10153493373097350_10153493386227350",
                                "like_count":1,
                                "message":"I think the originals are easier to read! I had relied on the kindness of others for my Doom Patrol reading back in the day and figured that it was about time I paid the creators.",
                                "user_likes":"0"
                            },
                            
                            {
                                "can_remove":"1",
                                "created_time":"2015-07-27T01:25:55+0000",
                                "from":
                                    {
                                        "id":"10203509649367805",
                                        "name":"Curt Krone"
                                    },
                                "id":"10153493373097350_10153493406137350",
                                "like_count":0,
                                "message":"yeah, those huge bound volumes are pretty ungainly",
                                "user_likes":"0"
                            },
                            
                            {
                                "can_remove":"1",
                                "created_time":"2015-07-27T02:26:28+0000",
                                "from":
                                    {
                                        "id":"10203444793744799",
                                        "name":"Michele Liguori"
                                    },
                                "id":"10153493373097350_10153493487672350",
                                "like_count":1,
                                "message":"Time to sift through the long boxes...",
                                "user_likes":"0"
                            }
                        ],
                    "paging":
                        {
                            "cursors":
                                {
                                    "after":"WTI5dGJXVnVkRjlqZFhKemIzSTZNVEF4TlRNME9UTTBPRGMyTnpJek5UQTZNVFF6TnprMk16azRPQT09",
                                    "before":"WTI5dGJXVnVkRjlqZFhKemIzSTZNVEF4TlRNME9UTXpOek0wTURjek5UQTZNVFF6TnprMU9UZ3lPUT09"
                                }
                        }
                },
            "created_time":"2015-07-27T01:16:50+0000",
            "from":
                {
                    "id":"728337349",
                    "name":"Shannon Posniewski"
                },
            "icon":"https:\/\/www.facebook.com\/images\/icons\/photo.gif",
            "id":"728337349_10153493373097350",
            "is_expired":"0",
            "is_hidden":"0",
            "likes":
                {
                    "data":
                        [
                            
                            {
                                "id":"10153089297557881",
                                "name":"Anddy Archer"
                            },
                            
                            {
                                "id":"10203107561026388",
                                "name":"Matt Woomer"
                            },
                            
                            {
                                "id":"10202301320933504",
                                "name":"Katherine Murray"
                            },
                            
                            {
                                "id":"10203974939883485",
                                "name":"Craig Zinkievich"
                            },
                            
                            {
                                "id":"10155677489010467",
                                "name":"Rick Dakan"
                            },
                            
                            {
                                "id":"10203444793744799",
                                "name":"Michele Liguori"
                            },
                            
                            {
                                "id":"767612906590923",
                                "name":"Barbara Vorce"
                            },
                            
                            {
                                "id":"10100530071678918",
                                "name":"Jeff Hamilton"
                            },
                            
                            {
                                "id":"10203310154056382",
                                "name":"Ed Raber"
                            },
                            
                            {
                                "id":"10152256693352752",
                                "name":"Jenn Jumper"
                            },
                            
                            {
                                "id":"10152933949431494",
                                "name":"Nick Duguid"
                            }
                        ],
                    "paging":
                        {
                            "cursors":
                                {
                                    "after":"MTAxNTI5MzM5NDk0MzE0OTQ=",
                                    "before":"MTAxNTMwODkyOTc1NTc4ODE="
                                }
                        }
                },
            "link":"https:\/\/www.facebook.com\/photo.php?fbid=10153493373097350&set=a.449479422349.249021.728337349&type=1",
            "message":"Just finished reading the 1000+ page Doom Patrol Omnibus (the Grant Morrison run) and boy are my arms tired!",
            "object_id":"10153493373097350",
            "picture":"https:\/\/scontent.xx.fbcdn.net\/hphotos-xfp1\/v\/t1.0-9\/s130x130\/11796460_10153493373097350_4574787842559235164_n.jpg?oh=c2f7b7ec3fda8834bd7333c69817d91c&oe=5643904A",
            "privacy":
                {
                    "allow":"",
                    "deny":"",
                    "description":"Public",
                    "friends":"",
                    "value":"EVERYONE"
                },
            "status_type":"added_photos",
            "subscribed":"1",
            "type":"photo",
            "updated_time":"2015-07-27T02:26:28+0000"
        }
}